keras_callback_slack/__init__.py
keras_callback_slack/callback.py
keras_callback_slack-0.0.5.dist-info/LICENSE
keras_callback_slack-0.0.5.dist-info/METADATA
keras_callback_slack-0.0.5.dist-info/WHEEL
keras_callback_slack-0.0.5.dist-info/top_level.txt
keras_callback_slack-0.0.5.dist-info/RECORD
