Metadata-Version: 2.1
Name: keras-callback-slack
Version: 0.0.5
Summary: keras custom callback for slack
Home-page: https://github.com/ken11/keras_callback_slack
Author: ken
Author-email: kent.adachi@adachi-honten.net
License: UNKNOWN
Keywords: keras callback slack notification
Platform: UNKNOWN
Classifier: Programming Language :: Python :: 3
Classifier: License :: OSI Approved :: MIT License
Classifier: Operating System :: OS Independent
Requires-Python: >=3.6
License-File: LICENSE
Requires-Dist: keras (>=2.4)
Requires-Dist: matplotlib (>=3)
Requires-Dist: slack-sdk (>=3.5)
